PyQt6/Qt6/lib/libQt6WebEngineCore.so.6
PyQt6/Qt6/lib/libQt6WebEngineQuick.so.6
PyQt6/Qt6/lib/libQt6WebEngineQuickDelegatesQml.so.6
PyQt6/Qt6/lib/libQt6WebEngineWidgets.so.6
PyQt6/Qt6/libexec/QtWebEngineProcess
PyQt6/Qt6/libexec/qt.conf
PyQt6/Qt6/qml/QtWebEngine/libqtwebenginequickplugin.so
PyQt6/Qt6/qml/QtWebEngine/plugins.qmltypes
PyQt6/Qt6/qml/QtWebEngine/qmldir
PyQt6/Qt6/qml/QtWebEngine/ControlsDelegates/AlertDialog.qml
PyQt6/Qt6/qml/QtWebEngine/ControlsDelegates/AuthenticationDialog.qml
PyQt6/Qt6/qml/QtWebEngine/ControlsDelegates/AutofillPopup.qml
PyQt6/Qt6/qml/QtWebEngine/ControlsDelegates/ColorDialog.qml
PyQt6/Qt6/qml/QtWebEngine/ControlsDelegates/ConfirmDialog.qml
PyQt6/Qt6/qml/QtWebEngine/ControlsDelegates/DirectoryPicker.qml
PyQt6/Qt6/qml/QtWebEngine/ControlsDelegates/FilePicker.qml
PyQt6/Qt6/qml/QtWebEngine/ControlsDelegates/Menu.qml
PyQt6/Qt6/qml/QtWebEngine/ControlsDelegates/MenuItem.qml
PyQt6/Qt6/qml/QtWebEngine/ControlsDelegates/MenuSeparator.qml
PyQt6/Qt6/qml/QtWebEngine/ControlsDelegates/PromptDialog.qml
PyQt6/Qt6/qml/QtWebEngine/ControlsDelegates/ToolTip.qml
PyQt6/Qt6/qml/QtWebEngine/ControlsDelegates/TouchHandle.qml
PyQt6/Qt6/qml/QtWebEngine/ControlsDelegates/TouchSelectionMenu.qml
PyQt6/Qt6/qml/QtWebEngine/ControlsDelegates/WebEngineQuickDelegatesQml.qmltypes
PyQt6/Qt6/qml/QtWebEngine/ControlsDelegates/libqtwebenginequickdelegatesplugin.so
PyQt6/Qt6/qml/QtWebEngine/ControlsDelegates/qmldir
PyQt6/Qt6/resources/icudtl.dat
PyQt6/Qt6/resources/qtwebengine_devtools_resources.pak
PyQt6/Qt6/resources/qtwebengine_resources.pak
PyQt6/Qt6/resources/qtwebengine_resources_100p.pak
PyQt6/Qt6/resources/qtwebengine_resources_200p.pak
PyQt6/Qt6/resources/v8_context_snapshot.bin
PyQt6/Qt6/translations/qtwebengine_ca.qm
PyQt6/Qt6/translations/qtwebengine_de.qm
PyQt6/Qt6/translations/qtwebengine_en.qm
PyQt6/Qt6/translations/qtwebengine_es.qm
PyQt6/Qt6/translations/qtwebengine_ka.qm
PyQt6/Qt6/translations/qtwebengine_ko.qm
PyQt6/Qt6/translations/qtwebengine_lg.qm
pyqt6_webengine_qt6-6.10.0.dist-info/LICENSE
pyqt6_webengine_qt6-6.10.0.dist-info/METADATA
pyqt6_webengine_qt6-6.10.0.dist-info/WHEEL
pyqt6_webengine_qt6-6.10.0.dist-info/RECORD
