Metadata-Version: 2.1
Name: PyQt6-WebEngine-Qt6
Version: 6.10.0
Summary: The subset of a Qt installation needed by PyQt6-WebEngine.
Home-page: https://www.riverbankcomputing.com/software/pyqt/
Author: Riverbank Computing Limited
Author-email: info@riverbankcomputing.com
License: LGPL v3
Platform: Linux
Platform: macOS
Platform: Windows
